run.py
tickets/__init__.py
tickets/core.py
tickets/movies.py
tickets/showes.py
tickets/trains.py
tickets/utils.py
tickets/datas/cities.dat
tickets/datas/stations.dat
tickets-0.3.0.dist-info/DESCRIPTION.rst
tickets-0.3.0.dist-info/METADATA
tickets-0.3.0.dist-info/RECORD
tickets-0.3.0.dist-info/WHEEL
tickets-0.3.0.dist-info/entry_points.txt
tickets-0.3.0.dist-info/metadata.json
tickets-0.3.0.dist-info/top_level.txt
