Metadata-Version: 2.0
Name: tickets
Version: 0.3.0
Summary: Train tickets query via command line.
Home-page: https://github.com/protream/tickets
Author: protream
Author-email: protream@gmail.com
License: MIT
Platform: any
Classifier: Environment :: Console
Classifier: Programming Language :: Python
Classifier: Programming Language :: Python :: 3
Classifier: Programming Language :: Python :: 3.1
Classifier: Programming Language :: Python :: 3.2
Classifier: Programming Language :: Python :: 3.3
Classifier: Programming Language :: Python :: 3.4
Classifier: Programming Language :: Python :: 3.5
Classifier: Programming Language :: Python :: Implementation :: CPython
Requires-Dist: bs4
Requires-Dist: prettytable
Requires-Dist: requests
